MANIFEST.in
probe_cloud.py
setup.py
probe/__init__.py
probe/cloud/__init__.py
probe/cloud/cloud.py
probe/cloud/fabfile.py
probe/cloud/logger.py
probe/cloud/rdir_watcher.py
probe/cloud/cfg/cloud.cfg
probe/cloud/cfg/logging.yml
probe_cloud.egg-info/PKG-INFO
probe_cloud.egg-info/SOURCES.txt
probe_cloud.egg-info/dependency_links.txt
probe_cloud.egg-info/entry_points.txt
probe_cloud.egg-info/namespace_packages.txt
probe_cloud.egg-info/requires.txt
probe_cloud.egg-info/top_level.txt
probe_cloud.egg-info/zip-safe