Metadata-Version: 1.0
Name: probe-cloud
Version: 0.1.24
Summary: cloud utils for probe packages
Home-page: UNKNOWN
Author: Petr Zikan
Author-email: zikan.p@gmail.com
License: GPLv3
Platform: UNKNOWN
